fpdet/__init__.py
fpdet/_dcore.py
fpdet/_dmatrix.py
fpdet/_numpy_core.py
fpdet-1.0.4.dist-info/LICENSE
fpdet-1.0.4.dist-info/METADATA
fpdet-1.0.4.dist-info/WHEEL
fpdet-1.0.4.dist-info/top_level.txt
fpdet-1.0.4.dist-info/RECORD
