Metadata-Version: 2.1
Name: fpdet
Version: 1.0.4
Summary: Basic analytical functions for a few-photon light detection
Home-page: https://github.com/vongostev/fpdet
Author: Pavel Gostev
Author-email: gostev.pavel@physics.msu.ru
License: UNKNOWN
Platform: UNKNOWN
Classifier: Programming Language :: Python :: 3
Classifier: License :: OSI Approved :: MIT License
Classifier: Operating System :: OS Independent
Requires-Python: >=3.6
Requires-Dist: numpy
Requires-Dist: scipy
